CHANGELOG.md
LICENSE
kaspa-1.0.1.post2.dist-info/METADATA
kaspa-1.0.1.post2.dist-info/WHEEL
kaspa-1.0.1.post2.dist-info/licenses/LICENSE
kaspa/__init__.py
kaspa/__init__.pyi
kaspa/kaspa.cpython-311-darwin.so
kaspa/py.typed
kaspa-1.0.1.post2.dist-info/RECORD
