Metadata-Version: 2.4
Name: kaspa
Version: 1.0.1.post2
Classifier: Development Status :: 4 - Beta
Classifier: Programming Language :: Python
Classifier: Programming Language :: Rust
License-File: LICENSE
Summary: Kaspa Python SDK
License-Expression: ISC
Requires-Python: >=3.9, <=3.14
Project-URL: Source, https://github.com/aspectron/rusty-kaspa/tree/python/python
Project-URL: Changelog, https://github.com/aspectron/rusty-kaspa/tree/python/python/CHANGELOG.md
